pagure_exporter/__init__.py
pagure_exporter/conf/__init__.py
pagure_exporter/conf/standard.py
pagure_exporter/dest/__init__.py
pagure_exporter/main.py
pagure_exporter/view/__init__.py
pagure_exporter/view/dcrt.py
pagure_exporter/view/misc.py
pagure_exporter/view/repo.py
pagure_exporter/view/stat.py
pagure_exporter/view/tkts.py
pagure_exporter/work/__init__.py
pagure_exporter/work/keep.py
pagure_exporter/work/repo.py
pagure_exporter/work/stat.py
pagure_exporter/work/tkts.py
pagure_exporter-0.1.4.dist-info/LICENSE
pagure_exporter-0.1.4.dist-info/METADATA
pagure_exporter-0.1.4.dist-info/WHEEL
pagure_exporter-0.1.4.dist-info/entry_points.txt
pagure_exporter-0.1.4.dist-info/RECORD
