Metadata-Version: 2.3
Name: pagure-exporter
Version: 0.1.4
Summary: Simple exporter tool that helps migrate repository files, data assets and issue tickets from projects on Pagure to GitLab
License: GPL-3.0-or-later
Keywords: fedora,pagure,gitlab
Author: Akashdeep Dhar
Author-email: akashdeep.dhar@gmail.com
Maintainer: Akashdeep Dhar
Maintainer-email: akashdeep.dhar@gmail.com
Requires-Python: >=3.11,<4.0
Classifier: Development Status :: 4 - Beta
Classifier: Environment :: Console
Classifier: Intended Audience :: Developers
Classifier: License :: OSI Approved :: GNU General Public License v3 or later (GPLv3+)
Classifier: Natural Language :: English
Classifier: Operating System :: POSIX :: Linux
Classifier: Programming Language :: Python :: 3
Classifier: Programming Language :: Python :: 3.11
Classifier: Programming Language :: Python :: 3.12
Classifier: Programming Language :: Python :: 3.13
Classifier: Topic :: Software Development
Classifier: Topic :: Software Development :: Version Control :: Git
Classifier: Topic :: System :: Archiving
Classifier: Topic :: System :: Networking
Classifier: Topic :: Utilities
Requires-Dist: GitPython (>=3.1.0,<4.0.0)
Requires-Dist: click (>=8.1.3,<9.0.0)
Requires-Dist: python-gitlab (>=3.14.0)
Requires-Dist: requests (>=2.28.0,<3.0.0)
Project-URL: Documentation, https://github.com/gridhead/pagure-exporter/blob/main/README.md
Project-URL: Homepage, https://github.com/gridhead/pagure-exporter
Project-URL: Repository, https://github.com/gridhead/pagure-exporter
